unique_df/__init__.py
unique_df/enforce_uniqueness.py
unique_df-1.0.dist-info/METADATA
unique_df-1.0.dist-info/WHEEL
unique_df-1.0.dist-info/top_level.txt
unique_df-1.0.dist-info/RECORD
