Metadata-Version: 2.1
Name: unique-df
Version: 1.0
Summary: Concatenate two dfs and return only unique ionstances
Author: Pierre Liebenberg
Author-email: pierrelieb@gmail.com
